csvthd/__init__.py
csvthd/__main__.py
csvthd/__version__.py
csvthd/cli.py
csvthd/commandline.py
csvthd/config.py
csvthd/exceptions.py
csvthd/filters.py
csvthd/reducers.py
csvthd/transactions.py
csvthd-0.6.1.dist-info/METADATA
csvthd-0.6.1.dist-info/WHEEL
csvthd-0.6.1.dist-info/entry_points.txt
csvthd-0.6.1.dist-info/RECORD
