Metadata-Version: 2.1
Name: csvthd
Version: 0.6.1
Summary: CSV Transaction History Detective
Home-page: https://gitlab.com/DrTexx/csv-transaction-history-detective/
License: AGPL-3.0-only
Keywords: finance,csv,transactions,tax,accounting
Author: DrTexx
Author-email: denver.opensource@tutanota.com
Requires-Python: >=3.8,<4.0
Classifier: License :: OSI Approved :: GNU Affero General Public License v3
Classifier: Programming Language :: Python :: 3
Classifier: Programming Language :: Python :: 3.8
Classifier: Programming Language :: Python :: 3.9
Classifier: Programming Language :: Python :: 3.10
Classifier: Programming Language :: Python :: 3.11
Classifier: Programming Language :: Python :: 3.12
Classifier: Programming Language :: Python :: 3.13
Requires-Dist: click (>=8.1.3,<9.0.0)
Project-URL: Documentation, https://gitlab.com/DrTexx/csv-transaction-history-detective/#getting-started
Project-URL: Repository, https://gitlab.com/DrTexx/csv-transaction-history-detective/
